CHANGELOG.rst
DESCRIPTION.rst
MANIFEST.in
README.rst
setup.py
hcpmqe.egg-info/PKG-INFO
hcpmqe.egg-info/SOURCES.txt
hcpmqe.egg-info/dependency_links.txt
hcpmqe.egg-info/entry_points.txt
hcpmqe.egg-info/requires.txt
hcpmqe.egg-info/top_level.txt
hcpmqelib/__init__.py
hcpmqelib/__main__.py
hcpmqelib/conf/__init__.py
hcpmqelib/conf/args.py
hcpmqelib/conf/config.py
hcpmqelib/db/__init__.py
hcpmqelib/db/csv.py
hcpmqelib/db/db.py
hcpmqelib/log/__init__.py
hcpmqelib/log/logging.py
hcpmqelib/mqe/__init__.py
hcpmqelib/mqe/query.py
hcpmqelib/mqe/template.py
hcpmqelib/ui/__init__.py
hcpmqelib/ui/eventloop.py
hcpmqelib/ui/layout.py
hcpmqelib/version/__init__.py