Metadata-Version: 1.1
Name: hcpmqe
Version: 2.0.3
Summary: hcpmqe - HCP Metadata Query Tool
Home-page: https://hcpmqe.readthedocs.io
Author: Thorsten Simons
Author-email: sw@snomis.eu
License: MIT
Keywords: HCP MQE Hitachi Content Platform
Platform: UNKNOWN
Classifier: Development Status :: 5 - Production/Stable
Classifier: Intended Audience :: System Administrators
Classifier: Topic :: System :: Archiving
Classifier: License :: OSI Approved :: MIT License
Classifier: Programming Language :: Python :: 3
Classifier: Operating System :: OS Independent
Classifier: Natural Language :: English
